noto/__init__.py
noto/main.py
noto/model.py
noto/cli/__init__.py
noto/cli/interactive.py
noto/cli/output.py
noto/cli/parser.py
noto/note/__init__.py
noto/note/delete.py
noto/note/read.py
noto/note/update.py
noto/note/write.py
noto-0.0.1.dist-info/LICENSE
noto-0.0.1.dist-info/METADATA
noto-0.0.1.dist-info/WHEEL
noto-0.0.1.dist-info/entry_points.txt
noto-0.0.1.dist-info/top_level.txt
noto-0.0.1.dist-info/RECORD
