Metadata-Version: 2.1
Name: noto
Version: 0.0.1
Summary: Non-Deterministic Note Box
Author-email: ctcq <homepage.ctcq@gmail.com>
License: MIT
Keywords: notes,fun
Classifier: Programming Language :: Python :: 3
Requires-Python: >=3.7
License-File: LICENSE
Requires-Dist: SQLAlchemy (==2.0.0rc3)
